README.txt
bootstrap.py
buildout.cfg
plonesite.cfg
setup.py
tests.py
docs/CONTRIBUTORS.txt
docs/HISTORY.txt
docs/LICENSE.txt
mr/__init__.py
mr.importer.egg-info/PKG-INFO
mr.importer.egg-info/SOURCES.txt
mr.importer.egg-info/dependency_links.txt
mr.importer.egg-info/entry_points.txt
mr.importer.egg-info/requires.txt
mr.importer.egg-info/top_level.txt
mr/importer/__init__.py
sample_data/README.txt
sample_data/index.html
sample_data/sample.xls
sample_data/a/index.html
sample_data/ac/index.html
sample_data/condimentum/index.html
sample_data/cursus/index.html
sample_data/dis/index.html
sample_data/fames/index.html
sample_data/gravida/index.html
sample_data/id/index.html
sample_data/integer/index.html
sample_data/libero/index.html
sample_data/mi/index.html
sample_data/mollis/index.html
sample_data/nec/index.html
sample_data/nulla/index.html
sample_data/nullam/index.html
sample_data/pede/index.html
sample_data/phasellus/index.html
sample_data/platea/index.html
sample_data/porta/index.html
sample_data/risus/index.html