Metadata-Version: 1.0
Name: mr.importer
Version: 1.0a5
Summary: Easily import static HTML websites on the file system into Plone
Home-page: https://github.com/collective/parse2plone
Author: Alex Clark
Author-email: aclark@aclark.net
License: UNKNOWN
Platform: UNKNOWN
Classifier: Framework :: Buildout
Classifier: Framework :: Plone
